ctpcrunch/CTP.py
ctpcrunch/__init__.py
ctpcrunch/_utils.py
ctpcrunch/cogwheel.py
ctpcrunch/nestcog.py
ctpcrunch/nested.py
ctpcrunch/phfree.py
ctpcrunch/core/__init__.py
ctpcrunch/core/algorithms.py
ctpcrunch/core/array.py
ctpcrunch/core/generators.py
ctpcrunch/core/numbers.py
ctpcrunch/core/test/__init__.py
ctpcrunch/core/test/test_numbers.py
ctpcrunch-0.0.1.dist-info/METADATA
ctpcrunch-0.0.1.dist-info/WHEEL
ctpcrunch-0.0.1.dist-info/licenses/LICENSE
ctpcrunch-0.0.1.dist-info/RECORD
