Metadata-Version: 2.3
Name: ctpcrunch
Version: 0.0.1
Summary: A small package to compute coherence order transfer paths
Author-email: Steffen Böckmann <steffen.boeckmann@uni-muenster.de>
Maintainer-email: Steffen Böckmann <steffen.boeckmann@uni-muenster.de>
License-File: LICENSE
Classifier: License :: OSI Approved :: MIT License
Classifier: Operating System :: OS Independent
Classifier: Programming Language :: Python :: 3
Requires-Python: >=3.10
Requires-Dist: numba>=0.58
Requires-Dist: numpy>=1.22
